sphinx_deployment/__init__.py
sphinx_deployment/__main__.py
sphinx_deployment/_version.py
sphinx_deployment/_version.pyi
sphinx_deployment/cli.py
sphinx_deployment/py.typed
sphinx_deployment/sphinx_ext.py
sphinx_deployment/_static/templates/redirect.html
sphinx_deployment/_static/templates/sphinx_deployment_dll.html
sphinx_deployment/_static/templates/versions.js
sphinx_deployment/_static/theme/rtd/rtd.css
sphinx_deployment/_static/theme/rtd/rtd.js_t
sphinx_deployment-0.0.25.dist-info/LICENSE
sphinx_deployment-0.0.25.dist-info/METADATA
sphinx_deployment-0.0.25.dist-info/WHEEL
sphinx_deployment-0.0.25.dist-info/entry_points.txt
sphinx_deployment-0.0.25.dist-info/top_level.txt
sphinx_deployment-0.0.25.dist-info/RECORD
